[
  {
    "title": "푸르닝데이 · 2026 정기총회(AGM)",
    "date": "2026-03-21",
    "category": "정기총회",
    "emoji": "🌱",
    "image": "images/garden/band-1.jpg"
  },
  {
    "title": "봄 장미 교육",
    "date": "2026-04-18",
    "category": "교육",
    "emoji": "🌷",
    "image": "images/garden/r120.jpg"
  },
  {
    "title": "서울장미축제 참여 (중랑구 MOU)",
    "date": "2026-05-15",
    "category": "축제",
    "emoji": "🌹",
    "image": "images/garden/feature-1.jpg"
  },
  {
    "title": "여름철 장미 관리 교육",
    "date": "2026-06-13",
    "category": "교육",
    "emoji": "☀️",
    "image": "images/garden/r57.jpg"
  },
  {
    "title": "6월 한국장미회 정기모임 (치치의 장미정원)",
    "date": "2026-06-20",
    "time": "09:00 (더위로 조금 일찍 시작해요)",
    "place": "이천시 백사면 현방리 374-7, 치치의 장미정원",
    "category": "정기모임",
    "emoji": "🌹",
    "image": "images/garden/band-4.jpg",
    "summary": "기후변화 시대의 장미정원",
    "details": "소요 시간 · 약 2시간\n준비물 · 모자·양산 필수, 음료수 및 간식 필수\n\n[프로그램]\n1. 정원 소개 (20~30분)\n · 치치의 장미정원 조성 배경\n · 장미정원 운영 과정\n · 토양·배수·기후 문제와 개선 과정\n · 기후변화와 장미정원 관리\n\n2. 정원 현장 투어 (30분)\n · 정원1·정원2·정원3 답사\n · 과습 및 생육 차이 사례\n · 녹비작물 및 토양개선 현황 소개\n · 실제 운영 과정과 실패·성공 사례 공유\n\n3. 회원 현장 토론 (20~30분)\n · 정원 운영 및 개선 방향 의견 나눔\n · 품종·토양·배수 등 경험 공유\n\n4. 마무리 (10분)\n · 질의응답\n · 기념 촬영\n\n[행사 특징]\n · 꽃 감상 중심이 아닌 실제 정원 운영 사례 공유\n · 기후변화 시대 장미정원 관리에 대한 현장 교육\n · 회원들의 경험과 의견을 함께 나누는 참여형 프로그램"
  },
  {
    "title": "장미정원 투어 (1박 2일)",
    "date": "2026-09-12",
    "category": "월간모임",
    "emoji": "🚌",
    "image": "images/garden/band-3.jpg"
  },
  {
    "title": "세계평화의 장미정원 조성",
    "date": "2026-10-10",
    "category": "정원",
    "emoji": "🕊️",
    "image": "images/garden/r30.jpg"
  },
  {
    "title": "장미 집중 교육",
    "date": "2026-11-14",
    "category": "교육",
    "emoji": "📚",
    "image": "images/garden/band-2.jpg"
  },
  {
    "title": "송년회",
    "date": "2026-12-12",
    "category": "행사",
    "emoji": "🎉",
    "image": "images/garden/r126.jpg"
  }
]
